edc_label/__init__.py
edc_label/admin.py
edc_label/admin_site.py
edc_label/apps.py
edc_label/auth_objects.py
edc_label/auths.py
edc_label/constants.py
edc_label/job_result.py
edc_label/lab_printers_mixin.py
edc_label/label.py
edc_label/label_template.py
edc_label/models.py
edc_label/navbars.py
edc_label/printer.py
edc_label/printers_mixin.py
edc_label/subject_label.py
edc_label/urls.py
edc_label/view_mixins.py
edc_label/migrations/0001_initial.py
edc_label/migrations/0002_alter_zpllabeltemplates_options.py
edc_label/migrations/0003_alter_zpllabeltemplates_device_created_and_more.py
edc_label/migrations/0004_alter_zpllabeltemplates_options_and_more.py
edc_label/migrations/0005_remove_zpllabeltemplates_edc_label_z_modifie_79a6b3_idx_and_more.py
edc_label/migrations/__init__.py
edc_label/static/edc_label/.DS_Store
edc_label/static/edc_label/js/BrowserPrint-3.0.216.min.js
edc_label/static/edc_label/js/edc_label.js
edc_label/static/edc_label/label_templates/aliquot.lbl
edc_label/static/edc_label/label_templates/box.lbl
edc_label/static/edc_label/label_templates/manifest.lbl
edc_label/static/edc_label/label_templates/requisition.lbl
edc_label/templates/edc_label/browser_print_labels.html
edc_label/templates/edc_label/home.html
edc_label/templates/edc_label/print_button.html
edc_label/templates/edc_label/printer_config.html
edc_label/templates/edc_label/printer_setup.html
edc_label/templatetags/__init__.py
edc_label/templatetags/edc_label_extras.py
edc_label/tests/__init__.py
edc_label/tests/test_settings.py
edc_label/tests/etc/user-aes-local.key
edc_label/tests/etc/user-aes-restricted.key
edc_label/tests/etc/user-rsa-local-private.pem
edc_label/tests/etc/user-rsa-local-public.pem
edc_label/tests/etc/user-rsa-restricted-private.pem
edc_label/tests/etc/user-rsa-restricted-public.pem
edc_label/tests/etc/user-salt-local.key
edc_label/tests/etc/user-salt-restricted.key
edc_label/tests/tests/__init__.py
edc_label/tests/tests/test_label.py
edc_label/views/__init__.py
edc_label-1.0.0.dist-info/AUTHORS
edc_label-1.0.0.dist-info/LICENSE
edc_label-1.0.0.dist-info/METADATA
edc_label-1.0.0.dist-info/WHEEL
edc_label-1.0.0.dist-info/top_level.txt
edc_label-1.0.0.dist-info/RECORD
